odoo/addons/sale_exception_product_sale_manufactured_for/README.rst
odoo/addons/sale_exception_product_sale_manufactured_for/__init__.py
odoo/addons/sale_exception_product_sale_manufactured_for/__manifest__.py
odoo/addons/sale_exception_product_sale_manufactured_for/data/exception_rule.xml
odoo/addons/sale_exception_product_sale_manufactured_for/demo/exception_rule.xml
odoo/addons/sale_exception_product_sale_manufactured_for/i18n/es.po
odoo/addons/sale_exception_product_sale_manufactured_for/i18n/it.po
odoo/addons/sale_exception_product_sale_manufactured_for/i18n/sale_exception_product_sale_manufactured_for.pot
odoo/addons/sale_exception_product_sale_manufactured_for/models/__init__.py
odoo/addons/sale_exception_product_sale_manufactured_for/models/sale_order.py
odoo/addons/sale_exception_product_sale_manufactured_for/readme/CONTRIBUTORS.md
odoo/addons/sale_exception_product_sale_manufactured_for/readme/CREDITS.md
odoo/addons/sale_exception_product_sale_manufactured_for/readme/DESCRIPTION.md
odoo/addons/sale_exception_product_sale_manufactured_for/static/description/icon.png
odoo/addons/sale_exception_product_sale_manufactured_for/static/description/index.html
odoo/addons/sale_exception_product_sale_manufactured_for/tests/__init__.py
odoo/addons/sale_exception_product_sale_manufactured_for/tests/test_sale_exception.py
odoo_addon_sale_exception_product_sale_manufactured_for-18.0.1.0.0.5.dist-info/METADATA
odoo_addon_sale_exception_product_sale_manufactured_for-18.0.1.0.0.5.dist-info/WHEEL
odoo_addon_sale_exception_product_sale_manufactured_for-18.0.1.0.0.5.dist-info/top_level.txt
odoo_addon_sale_exception_product_sale_manufactured_for-18.0.1.0.0.5.dist-info/RECORD
