Metadata-Version: 2.1
Name: odoo-addon-sale_exception_product_sale_manufactured_for
Version: 18.0.1.0.0.5
Requires-Python: >=3.10
Requires-Dist: odoo-addon-product_sale_manufactured_for==18.0.*
Requires-Dist: odoo-addon-sale_exception==18.0.*
Requires-Dist: odoo==18.0.*
Summary: The partner set in the sales order can order only if he/she has a commercial entity that is listed as one of the partners for which the products can be manufactured for.
Home-page: https://github.com/OCA/sale-workflow
License: AGPL-3
Author: Camptocamp, Odoo Community Association (OCA)
Author-email: support@odoo-community.org
Classifier: Programming Language :: Python
Classifier: Framework :: Odoo
Classifier: Framework :: Odoo :: 18.0
Classifier: License :: OSI Approved :: GNU Affero General Public License v3
